simple_package/__init__.py
simple_package/cli.py
simple_package/core.py
simple_package/utils.py
example_package_yzqq-0.1.0.dist-info/METADATA
example_package_yzqq-0.1.0.dist-info/WHEEL
example_package_yzqq-0.1.0.dist-info/entry_points.txt
example_package_yzqq-0.1.0.dist-info/licenses/LICENSE
example_package_yzqq-0.1.0.dist-info/RECORD
