Metadata-Version: 2.4
Name: example_package_yzqq
Version: 0.1.0
Summary: A simple Python package demonstrating uv packaging
Project-URL: Homepage, https://github.com/yourusername/simple-package
Project-URL: Documentation, https://github.com/yourusername/simple-package
Project-URL: Repository, https://github.com/yourusername/simple-package.git
Project-URL: Bug Tracker, https://github.com/yourusername/simple-package/issues
Author-email: Your Name <your.email@example.com>
License: MIT
License-File: LICENSE
Keywords: demo,packaging,uv
Classifier: Development Status :: 3 - Alpha
Classifier: Intended Audience :: Developers
Classifier: License :: OSI Approved :: MIT License
Classifier: Programming Language :: Python :: 3
Classifier: Programming Language :: Python :: 3.8
Classifier: Programming Language :: Python :: 3.9
Classifier: Programming Language :: Python :: 3.10
Classifier: Programming Language :: Python :: 3.11
Classifier: Programming Language :: Python :: 3.12
Requires-Python: >=3.8
Requires-Dist: click>=8.0.0
Requires-Dist: requests>=2.25.0
Provides-Extra: dev
Requires-Dist: black>=21.0; extra == 'dev'
Requires-Dist: flake8>=3.8; extra == 'dev'
Requires-Dist: mypy>=0.800; extra == 'dev'
Requires-Dist: pytest>=6.0; extra == 'dev'
Provides-Extra: test
Requires-Dist: pytest-cov>=2.0; extra == 'test'
Requires-Dist: pytest>=6.0; extra == 'test'
